<?xml version="1.0" encoding="euc-kr" ?>
<clientinfo>
	<desc>Ragnarok Client Information</desc>
	<servicetype>brazil</servicetype>
	<servertype>primary</servertype>
	<connection>
		<display>brAthena</display>
      		<address>185.203.119.11</address>
      		<port>6900</port>
      		<version>55</version>
      		<langtype>12</langtype>
		<registrationweb>www.brathena.com/registro</registrationweb>

		<yellow>
			<admin>2000000</admin>
		</yellow>

		<loading>
			<image>loading00.jpg</image>
			<image>loading01.jpg</image>
			<image>loading02.jpg</image>
			<image>loading03.jpg</image>
			<image>loading04.jpg</image>
			<image>loading05.jpg</image>
			<image>loading06.jpg</image>
		</loading>
   	</connection>

</clientinfo>